odoo/addons/partner_quality_log/README.rst
odoo/addons/partner_quality_log/__init__.py
odoo/addons/partner_quality_log/__manifest__.py
odoo/addons/partner_quality_log/i18n/es.po
odoo/addons/partner_quality_log/i18n/partner_quality_log.pot
odoo/addons/partner_quality_log/models/__init__.py
odoo/addons/partner_quality_log/models/quality_partner_log.py
odoo/addons/partner_quality_log/models/res_partner.py
odoo/addons/partner_quality_log/readme/CONTRIBUTORS.rst
odoo/addons/partner_quality_log/readme/DESCRIPTION.rst
odoo/addons/partner_quality_log/readme/USAGE.rst
odoo/addons/partner_quality_log/security/ir.model.access.csv
odoo/addons/partner_quality_log/static/description/icon.png
odoo/addons/partner_quality_log/static/description/index.html
odoo/addons/partner_quality_log/tests/__init__.py
odoo/addons/partner_quality_log/tests/test_quality_partner_log.py
odoo/addons/partner_quality_log/views/res_partner_views.xml
odoo_addon_partner_quality_log-16.0.1.0.0.2.dist-info/METADATA
odoo_addon_partner_quality_log-16.0.1.0.0.2.dist-info/WHEEL
odoo_addon_partner_quality_log-16.0.1.0.0.2.dist-info/top_level.txt
odoo_addon_partner_quality_log-16.0.1.0.0.2.dist-info/RECORD
